visualizer/__init__.py
visualizer/visualizer.py
visualizer_3d-0.3.4.dist-info/LICENSE
visualizer_3d-0.3.4.dist-info/METADATA
visualizer_3d-0.3.4.dist-info/WHEEL
visualizer_3d-0.3.4.dist-info/top_level.txt
visualizer_3d-0.3.4.dist-info/RECORD
