Metadata-Version: 2.1
Name: visualizer-3d
Version: 0.3.4
Summary: Tool for three-dimensional animations of geometries like FE meshes
Author-email: Jonas Kneifl <jonas.kneifl@itm.uni-stuttgart.com>
Project-URL: Homepage, https://github.com/jkneifl/visualizer
Project-URL: Issues, https://github.com/jkneifl/visualizer/issues
Keywords: visualiztion,mesh
Classifier: Programming Language :: Python :: 3
Classifier: License :: OSI Approved :: MIT License
Classifier: Operating System :: OS Independent
Requires-Python: >=3.8
License-File: LICENSE
Requires-Dist: PyOpenGL>=3.1.6
Requires-Dist: PyQt6>=6.3.0
Requires-Dist: pyqtgraph>=0.12.3
Requires-Dist: opencv-python
Requires-Dist: matplotlib
Requires-Dist: Pillow
Requires-Dist: numpy
